{
  "createdAt": "2023-04-18T08:05:28.752Z",
  "updatedAt": "2023-04-18T13:04:38.270Z",
  "id": "1",
  "name": "Header Auth account",
  "data": {
    "name": "",
    "value": "={{ process.env.XX }}"
  },
  "type": "httpHeaderAuth",
  "nodesAccess": [
    {
      "nodeType": "n8n-nodes-base.graphql",
      "date": "2023-04-18T08:05:28.733Z"
    },
    {
      "nodeType": "n8n-nodes-base.wait",
      "date": "2023-04-18T08:05:28.733Z"
    },
    {
      "nodeType": "n8n-nodes-base.webhook",
      "date": "2023-04-18T08:05:28.733Z"
    }
  ]
}